<results serviceId="EDAR_Cartuja_Perfil_Out">
	<example-set>
		<example>
			<cluster>cluster_0</cluster>
			<Indicador>average(O_NTk_conc)</Indicador>
			<valor>0.507</valor>
		</example>
		<example>
			<cluster>cluster_0</cluster>
			<Indicador>average(O_DQOt_masa)</Indicador>
			<valor>-0.574</valor>
		</example>
		<example>
			<cluster>cluster_0</cluster>
			<Indicador>average(O_DBO5t_masa)</Indicador>
			<valor>-0.551</valor>
		</example>
	<example-set>
<results serviceId="EDAR_Cartuja_Perfil_Out">
